{
  "parent": "vibraniumtechnologies:recipes/root",
  "rewards": {
    "recipes": [
      "vibraniumtechnologies:coal_nugget"
    ]
  },
  "criteria": {
    "has_coal": {
      "trigger": "minecraft:inventory_changed",
      "conditions": {
        "items": [
          {
            "items": [
              "minecraft:coal"
            ]
          }
        ]
      }
    },
    "has_the_recipe": {
      "trigger": "minecraft:recipe_unlocked",
      "conditions": {
        "recipe": "vibraniumtechnologies:coal_nugget"
      }
    }
  },
  "requirements": [
    [
      "has_coal",
      "has_the_recipe"
    ]
  ]
}